djangosaml2/__init__.py
djangosaml2/apps.py
djangosaml2/backends.py
djangosaml2/cache.py
djangosaml2/conf.py
djangosaml2/exceptions.py
djangosaml2/middleware.py
djangosaml2/overrides.py
djangosaml2/signals.py
djangosaml2/urls.py
djangosaml2/utils.py
djangosaml2/views.py
djangosaml2/templates/djangosaml2/auth_error.html
djangosaml2/templates/djangosaml2/echo_attributes.html
djangosaml2/templates/djangosaml2/example_post_binding_form.html
djangosaml2/templates/djangosaml2/login_error.html
djangosaml2/templates/djangosaml2/logout_error.html
djangosaml2/templates/djangosaml2/post_binding_form.html
djangosaml2/templates/djangosaml2/wayf.html
djangosaml2/templatetags/__init__.py
djangosaml2/templatetags/idplist.py
djangosaml2/tests/__init__.py
djangosaml2/tests/auth_response.py
djangosaml2/tests/conf.py
djangosaml2/tests/idpcert.csr
djangosaml2/tests/idpcert.key
djangosaml2/tests/idpcert.pem
djangosaml2/tests/mycert.csr
djangosaml2/tests/mycert.key
djangosaml2/tests/mycert.pem
djangosaml2/tests/remote_metadata.xml
djangosaml2/tests/remote_metadata_no_idp.xml
djangosaml2/tests/remote_metadata_one_idp.xml
djangosaml2/tests/remote_metadata_post_binding.xml
djangosaml2/tests/remote_metadata_three_idps.xml
djangosaml2/tests/sp_metadata.xml
djangosaml2/tests/spcert.csr
djangosaml2/tests/spcert.key
djangosaml2/tests/spcert.pem
djangosaml2/tests/utils.py
djangosaml2/tests/attribute-maps/django_saml_uri.py
djangosaml2/tests/attribute-maps/saml_uri.py
djangosaml2-1.11.1.dist-info/licenses/COPYING
djangosaml2-1.11.1.dist-info/METADATA
djangosaml2-1.11.1.dist-info/WHEEL
djangosaml2-1.11.1.dist-info/top_level.txt
djangosaml2-1.11.1.dist-info/RECORD
