Metadata-Version: 2.4
Name: djangosaml2
Version: 1.11.1
Summary: pysaml2 integration for Django
Home-page: https://github.com/IdentityPython/djangosaml2
Download-URL: https://pypi.org/project/djangosaml2/
Author: Yaco Sistemas and independent contributors
Author-email: lorenzo.gil.sanchez@gmail.com
Maintainer: Giuseppe De Marco
License: Apache 2.0
Keywords: django,pysaml2,sso,saml2,federated authentication,authentication
Classifier: Development Status :: 5 - Production/Stable
Classifier: Environment :: Web Environment
Classifier: Framework :: Django
Classifier: Framework :: Django :: 4.2
Classifier: Framework :: Django :: 5.0
Classifier: Framework :: Django :: 5.1
Classifier: Intended Audience :: Developers
Classifier: License :: OSI Approved :: Apache Software License
Classifier: Operating System :: OS Independent
Classifier: Programming Language :: Python
Classifier: Programming Language :: Python :: 3.9
Classifier: Programming Language :: Python :: 3.10
Classifier: Programming Language :: Python :: 3.11
Classifier: Programming Language :: Python :: 3.12
Classifier: Programming Language :: Python :: 3.13
Classifier: Topic :: Internet :: WWW/HTTP
Classifier: Topic :: Internet :: WWW/HTTP :: WSGI
Classifier: Topic :: Security
Classifier: Topic :: Software Development :: Libraries :: Application Frameworks
Requires-Python: >=3.9
License-File: COPYING
Requires-Dist: defusedxml>=0.4.1
Requires-Dist: Django>=4.2
Requires-Dist: pysaml2>=6.5.1
Dynamic: author
Dynamic: author-email
Dynamic: classifier
Dynamic: description
Dynamic: description-content-type
Dynamic: download-url
Dynamic: home-page
Dynamic: keywords
Dynamic: license
Dynamic: license-file
Dynamic: maintainer
Dynamic: requires-dist
Dynamic: requires-python
Dynamic: summary
